pit2ya/__init__.py
pit2ya/api.py
pit2ya/db.py
pit2ya/entry.py
pit2ya/toggl_wrap.py
Pit2ya-0.4.2.dist-info/METADATA
Pit2ya-0.4.2.dist-info/WHEEL
Pit2ya-0.4.2.dist-info/entry_points.txt
Pit2ya-0.4.2.dist-info/top_level.txt
Pit2ya-0.4.2.dist-info/RECORD
