Metadata-Version: 2.1
Name: Pit2ya
Version: 0.4.2
Summary: Ergonomic continuation of Toggl time entries
Home-page: https://github.com/Exr0nProjects/pit2ya
Author: Exr0n
Author-email: mail@exr0n.com
License: MIT
Keywords: toggl togglcli wrapper
Platform: UNKNOWN
Classifier: Programming Language :: Python :: 3
Classifier: License :: OSI Approved :: MIT License
Classifier: Operating System :: OS Independent
Requires-Dist: blessed (==1.17.6)
Requires-Dist: certifi (==2020.12.5)
Requires-Dist: chardet (==4.0.0)
Requires-Dist: click (==7.1.2)
Requires-Dist: click-completion (==0.5.2)
Requires-Dist: idna (==2.10)
Requires-Dist: inquirer (==2.7.0)
Requires-Dist: iterfzf (==0.5.0.20.0)
Requires-Dist: Jinja2 (==3.0.1)
Requires-Dist: loguru (==0.5.3)
Requires-Dist: MarkupSafe (==2.0.1)
Requires-Dist: notify-py (==0.3.1)
Requires-Dist: pbr (==5.5.1)
Requires-Dist: pendulum (==2.1.2)
Requires-Dist: PTable (==0.9.2)
Requires-Dist: python-dateutil (==2.8.1)
Requires-Dist: python-editor (==1.0.4)
Requires-Dist: pytzdata (==2020.1)
Requires-Dist: readchar (==2.0.1)
Requires-Dist: requests (==2.25.1)
Requires-Dist: shellingham (==1.4.0)
Requires-Dist: six (==1.16.0)
Requires-Dist: togglCli (==2.4.0)
Requires-Dist: urllib3 (==1.26.4)
Requires-Dist: validate-email (==1.3)
Requires-Dist: wcwidth (==0.2.5)
